crossenv/__init__.py
crossenv/__main__.py
crossenv/template.py
crossenv/utils.py
crossenv/scripts/_manylinux.py.tmpl
crossenv/scripts/cross-expose.py.tmpl
crossenv/scripts/distutils-sysconfig-patch.py.tmpl
crossenv/scripts/importlib-machinery-patch.py.tmpl
crossenv/scripts/importlib-metadata-patch.py.tmpl
crossenv/scripts/os-patch.py.tmpl
crossenv/scripts/packaging-tags-patch.py.tmpl
crossenv/scripts/pip-_vendor-distlib-scripts-patch.py.tmpl
crossenv/scripts/platform-patch.py.tmpl
crossenv/scripts/pywrapper.py.tmpl
crossenv/scripts/site.py.tmpl
crossenv/scripts/subprocess-patch.py.tmpl
crossenv/scripts/sys-patch.py.tmpl
crossenv/scripts/sysconfig-patch.py.tmpl
crossenv-1.6.1.dist-info/METADATA
crossenv-1.6.1.dist-info/WHEEL
crossenv-1.6.1.dist-info/licenses/LICENSE.txt
crossenv-1.6.1.dist-info/RECORD
