Metadata-Version: 2.4
Name: crossenv
Version: 1.6.1
Summary: A cross-compiling tool for Python extension modules
Project-URL: Homepage, https://github.com/robotpy/crossenv
Author-email: Benjamin Fogle <benfogle@gmail.com>
Maintainer-email: Dustin Spicuzza <dustin@virtualroadside.com>
License: Copyright (c) 2018 Benjamin Fogle
License-File: LICENSE.txt
Classifier: Development Status :: 4 - Beta
Classifier: Intended Audience :: Developers
Classifier: License :: OSI Approved :: MIT License
Classifier: Programming Language :: Python :: 3
Classifier: Topic :: Software Development :: Build Tools
Requires-Python: >=3.6
Requires-Dist: wheel
